{
  "0. Completed": [
    {
      "title": "Computer Architecture and Operating Systems",
      "code": "DLBCSCAOS01",
      "credit": 5,
      "type": "core",
      "completed": true
    },
    {
      "title": "Data Structures and Java Class Library",
      "code": "DLBCSDSJCL01",
      "credit": 5,
      "type": "core",
      "completed": true
    },
    {
      "title": "Introduction to Academic Work",
      "code": "DLBCSIAW01",
      "credit": 5,
      "type": "core",
      "completed": true
    },
    {
      "title": "Introduction to Computer Science",
      "code": "DLBCSICS01",
      "credit": 5,
      "type": "core",
      "completed": true
    },
    {
      "title": "Intercultural and Ethical Decision-Making",
      "code": "DLBCSIDM01",
      "credit": 5,
      "type": "core",
      "completed": true
    },
    {
      "title": "Mathematics I",
      "code": "DLBCSM101",
      "credit": 5,
      "type": "core",
      "completed": true
    },
    {
      "title": "Mathematics II",
      "code": "DLBCSM201",
      "credit": 5,
      "type": "core",
      "completed": true
    },
    {
      "title": "Object-oriented Programming with Java",
      "code": "DLBCSOOPJ01",
      "credit": 5,
      "type": "core",
      "completed": true
    },
    {
      "title": "Web Application Development",
      "code": "DLBCSWAD01",
      "credit": 5,
      "type": "core",
      "completed": true
    }
  ],
  "1. (HW/Proj)Courses Left": [
    {
      "title": "Project: Build a Data Mart in SQL",
      "credit": 5,
      "type": "core",
      "completed": false
    },
    {
      "title": "IT Law",
      "credit": 5,
      "type": "core",
      "completed": false
    },
    {
      "title": "Project: Software Engineering",
      "credit": 5,
      "type": "core",
      "completed": false
    },
    {
      "title": "Agile Project Management Model Engineering",
      "credit": 5,
      "type": "core",
      "completed": false
    },
    {
      "title": "Project: IT Service Management",
      "credit": 5,
      "type": "core",
      "completed": false
    },
    {
      "title": "Seminar: Current Topics in Computer Science",
      "credit": 5,
      "type": "core",
      "completed": false
    }
  ],
  "1.5 (HW/Proj)Studying": [
    {
      "title": "Cryptography",
      "credit": 5,
      "type": "core",
      "completed": false
    },
    {
      "title": "Project: Java and Web Development",
      "credit": 5,
      "type": "core",
      "completed": false
    }
  ],
  "2. (HW/Proj)Making": [
    {
      "title": "Collaborative Work @Easy",
      "credit": 5,
      "type": "read",
      "completed": false
    },
    {
      "title": "Computer Science and Society",
      "credit": 5,
      "type": "read",
      "completed": false
    }
  ],
  "3. (HW/Proj)Waiting for the result": [
    {
      "title": "Algorithms, Data Structures and Programming Languages",
      "credit": 5,
      "type": "waiting",
      "completed": false
    }
  ],
  "4. (Exam)Courses Left": [
    {
      "title": "Theoretical Computer Science and Mathematical Logic",
      "credit": 5,
      "type": "exam",
      "completed": false
    },
    {
      "title": "Statistics - Probability and Descriptive Statistics",
      "credit": 5,
      "type": "exam",
      "completed": false
    },
    {
      "title": "Requirements Engineering",
      "credit": 5,
      "type": "exam",
      "completed": false
    },
    {
      "title": "Specification",
      "credit": 5,
      "type": "exam",
      "completed": false
    },
    {
      "title": "Database Modeling and Database Systems",
      "credit": 5,
      "type": "exam",
      "completed": false
    },
    {
      "title": "IT Service Management",
      "credit": 5,
      "type": "exam",
      "completed": false
    },
    {
      "title": "Software Quality Assurance",
      "credit": 5,
      "type": "exam",
      "completed": false
    },
    {
      "title": "Introduction to Programming with Python",
      "credit": 5,
      "type": "exam",
      "completed": false
    }
  ],
  "5. (Exam)Studying": [
    {
      "title": "Computer Networks and Distributed Systems",
      "credit": 5,
      "type": "read",
      "completed": false
    }
  ],
  "6. (Exam)Preparing for the exam": [
    {
      "title": "Introduction to Data Protection and IT Security",
      "credit": 5,
      "type": "read",
      "completed": false
    }
  ],
  "7. (Exam)Waiting for the result": [],
  "8. Electives": [
    {
      "title": "EA1 (Elective)",
      "credit": 5,
      "type": "elective",
      "completed": false
    },
    {
      "title": "EA2 (Elective)",
      "credit": 5,
      "type": "elective",
      "completed": false
    },
    {
      "title": "EB1 (Elective)",
      "credit": 5,
      "type": "elective",
      "completed": false
    },
    {
      "title": "EB2 (Elective)",
      "credit": 5,
      "type": "elective",
      "completed": false
    }
  ],
  "9. Thesis": [
    {
      "title": "Bachelor Thesis",
      "credit": 9,
      "type": "core",
      "completed": false
    },
    {
      "title": "Colloquium",
      "credit": 1,
      "type": "core",
      "completed": false
    }
  ]
}